passy/__init__.py
passy/otp.py
passy/passy.py
passy-0.2.0.dist-info/LICENSE
passy-0.2.0.dist-info/WHEEL
passy-0.2.0.dist-info/METADATA
passy-0.2.0.dist-info/RECORD
